{"date":"2026-06-22","bookings":{"s1_slot_5_45":["mahprate"],"s1_slot_8_45":["mahprate"],"s1_slot_11_45":["mahprate","gsmaddal","gvssv","vijynn"],"s1_slot_11_30":["gsmaddal","mahprate","gvssv","vijynn"],"s1_slot_9_30":["gsmaddal","vijynn"],"s1_slot_9_0":["gvssv","sandykay"],"s1_slot_7_0":["gvssv","vamskb"],"s1_slot_9_45":["vijynn"],"s1_slot_10_0":["vamskb","pathuven"],"s1_slot_6_45":["pathuven"],"s1_slot_7_15":["pathuven","tinkusiv","sandykay"],"s1_slot_11_15":["tinkusiv","sandykay"],"s1_slot_11_0":["tinkusiv"],"s1_slot_10_15":["pathuven","kulsrika"]},"bookingLog":[{"user":"mahprate","slotLabel":"5:45 AM - 6:00 AM","date":"2026-06-22","bookedAt":"22/6/2026, 4:30:26 am"},{"user":"mahprate","slotLabel":"8:45 AM - 9:00 AM","date":"2026-06-22","bookedAt":"22/6/2026, 4:30:30 am"},{"user":"mahprate","slotLabel":"11:45 AM - 12:00 PM","date":"2026-06-22","bookedAt":"22/6/2026, 4:30:33 am"},{"user":"gsmaddal","slotLabel":"11:45 AM - 12:00 PM","date":"2026-06-22","bookedAt":"22/6/2026, 4:31:07 am"},{"user":"gsmaddal","slotLabel":"11:30 AM - 11:45 AM","date":"2026-06-22","bookedAt":"22/6/2026, 4:31:09 am"},{"user":"gsmaddal","slotLabel":"9:30 AM - 9:45 AM","date":"2026-06-22","bookedAt":"22/6/2026, 4:31:14 am"},{"user":"mahprate","slotLabel":"11:30 AM - 11:45 AM","date":"2026-06-22","bookedAt":"22/6/2026, 4:36:36 am"},{"user":"gvssv","slotLabel":"7:00 AM - 7:15 AM","date":"2026-06-22","bookedAt":"22/6/2026, 5:20:53 am"},{"user":"vijynn","slotLabel":"9:30 AM - 9:45 AM","date":"2026-06-22","bookedAt":"22/6/2026, 5:44:44 am"},{"user":"vijynn","slotLabel":"9:45 AM - 10:00 AM","date":"2026-06-22","bookedAt":"22/6/2026, 5:44:46 am"},{"user":"vamskb","slotLabel":"7:00 AM - 7:15 AM","date":"2026-06-22","bookedAt":"22/6/2026, 6:32:59 am"},{"user":"vamskb","slotLabel":"10:00 AM - 10:15 AM","date":"2026-06-22","bookedAt":"22/6/2026, 6:33:05 am"},{"user":"pathuven","slotLabel":"7:15 AM - 7:30 AM","date":"2026-06-22","bookedAt":"22/6/2026, 6:48:13 am"},{"user":"tinkusiv","slotLabel":"7:15 AM - 7:30 AM","date":"2026-06-22","bookedAt":"22/6/2026, 6:51:54 am"},{"user":"pathuven","slotLabel":"10:15 AM - 10:30 AM","date":"2026-06-22","bookedAt":"22/6/2026, 6:56:44 am"},{"user":"sandykay","slotLabel":"7:15 AM - 7:30 AM","date":"2026-06-22","bookedAt":"22/6/2026, 6:59:24 am"},{"user":"sandykay","slotLabel":"9:00 AM - 9:15 AM","date":"2026-06-22","bookedAt":"22/6/2026, 6:59:27 am"},{"user":"sandykay","slotLabel":"11:15 AM - 11:30 AM","date":"2026-06-22","bookedAt":"22/6/2026, 6:59:33 am"},{"user":"kulsrika","slotLabel":"10:15 AM - 10:30 AM","date":"2026-06-22","bookedAt":"22/6/2026, 9:35:40 am"}],"lastUpdated":"2026-06-22T04:05:40.676Z"}